{
  "products":[
    {
      "id": 1,
      "name": "USB 3.0 SanDisk, CZ73",
      "price": 500,
      "size": 128,
      "demension": "42.4 x 12.4 x 6.6 mm",
      "speed": "5 Gbit/s",
      "material": "Metal",
      "image": "https://dkstatics-public.digikala.com/digikala-products/722643.jpg?x-oss-process=image/resize,m_lfit,h_800,w_800/format,webp/quality,q_90",
      "available": true,
      "rating": 3.5 
    },
    {
      "id": 2,
      "name": "USB 2.0 HP, V150w",
      "price": 220,
      "size": 64,
      "demension": "20.1 x 12.1 x 5.5 mm",
      "speed": "4 Gbit/s",
      "material": "Plastic",
      "image": "https://dkstatics-public.digikala.com/digikala-products/86f8b8013f397853f709060bd2a1d8577607cdef_1639080552.jpg?x-oss-process=image/resize,m_lfit,h_800,w_800/format,webp/quality,q_90",
      "available": true,
      "rating": 4.5  
    },
    {
      "id": 3,
      "name": "USB 3.1 ADATA, UV320",
      "price": 260,
      "size": 32,
      "demension": "55 x 19.1 x 10.5 mm",
      "speed": "10 Gbit/s",
      "material": "Plastic",
      "image": "https://dkstatics-public.digikala.com/digikala-products/859394.jpg?x-oss-process=image/resize,m_lfit,h_800,w_800/format,webp/quality,q_90",
      "available": false,
      "rating": 2.5  
    },
    {
      "id": 4,
      "name": "Type-C QueenTech, C-PLUS",
      "price": 229.0,
      "size": 64,
      "demension": "30.1 x 15.1 x 7.5 mm",
      "speed": "8 Gbit/s",
      "material": "Plastic",
      "image": "https://dkstatics-public.digikala.com/digikala-products/de77a4c45a43dd3b5f7fa1c73006b7f70ccc60df_1641184037.jpg?x-oss-process=image/resize,m_lfit,h_800,w_800/format,webp/quality,q_90" ,
      "available": true,
      "rating": 3 
    },
    {
      "id": 5,
      "name": "USB Type-C SanDisk UltC",
      "price": 285,
      "size": 32,
      "demension": "60.0 x 12.0 x 8.1 mm",
      "speed": "12 Gbit/s",
      "material": "Plastic",
      "image": "https://dkstatics-public.digikala.com/digikala-products/767f741f9511e65a8a162dad124b0425ac7bdebd_1598040602.jpg?x-oss-process=image/resize,m_lfit,h_800,w_800/format,webp/quality,q_90",
      "available": false,
      "rating": 4  
    },
    {
      "id": 6,
      "name": "USB 2.0 HP, V212LB",
      "price": 275,
      "size": 32,
      "demension": "56.2 x 20.4 x 6.5 mm",
      "speed": "7 Gbit/s",
      "material": "Plastic",
      "image": "https://dkstatics-public.digikala.com/digikala-products/af6ecf7bf08dedf5c8a2e1289adbb1240b8301f7_1653400454.jpg?x-oss-process=image/resize,m_lfit,h_800,w_800/format,webp/quality,q_90",
      "available": false,
      "rating": 4.5  
    },
    {
      "id": 7,
      "name": "USB 3.2 ADATA, UR340",
      "price": 320,
      "size": 64,
      "demension": "29.1 x 11.1 x 5.5 mm",
      "speed": "10 Gbit/s",
      "material": "Metal",
      "image": "https://dkstatics-public.digikala.com/digikala-products/55af8a7ccccdf31d8cd7b2cf85e8b7be29390562_1695125928.jpg?x-oss-process=image/resize,m_lfit,h_800,w_800/format,webp/quality,q_90",
      "available": true,
      "rating": 2  
    },
    {
      "id": 8,
      "name": "USB 3.2 ADADA, UV150",
      "price": 248,
      "size": 32,
      "demension": "58.0 x 18.01 x 10.5 mm",
      "speed": "8 Gbit/s",
      "material": "Plastic",
      "image": "https://dkstatics-public.digikala.com/digikala-products/794a92424cbd77cb8832a1e285367e7bc54da3c8_1661750037.jpg?x-oss-process=image/resize,m_lfit,h_800,w_800/format,webp/quality,q_90",
      "available": true,
      "rating": 3.5  
    },
    {
      "id": 9,
      "name": "USB 2.0 Lexar, V40",
      "price": 173,
      "size": 32,
      "demension": "40.0 x 20.1 x 10.5 mm",
      "speed": "4 Gbit/s",
      "material": "Plastic",
      "image": "https://dkstatics-public.digikala.com/digikala-products/4867036.jpg?x-oss-process=image/resize,m_lfit,h_800,w_800/format,webp/quality,q_90",
      "available": false,
      "rating": 4  
    },
    {
      "id": 10,
      "name": "Type-C Samgporse, V150w",
      "price": 560,
      "size": 128,
      "demension": "65.1 x 20.3 x 8.5 mm",
      "speed": "15 Gbit/s",
      "material": "Plastic/Metal",
      "image": "https://dkstatics-public.digikala.com/digikala-products/85625615ef0baa4f07cab0703a192ae2a415acff_1699950538.jpg?x-oss-process=image/resize,m_lfit,h_800,w_800/format,webp/quality,q_90",
      "available": true,
      "rating": 3  
    },
    {
      "id": 11,
      "name": "Type-C SSK, SD301 SSD DRIVE",
      "price": 1800,
      "size": 1000,
      "demension": "80.1 x 20.5 x 10.5 mm",
      "speed": "30 Gbit/s",
      "material": "Metal",
      "image": "https://dkstatics-public.digikala.com/digikala-products/1195a4fae637c050341405fd65b872af568dce50_1695232035.jpg?x-oss-process=image/resize,m_lfit,h_800,w_800/format,webp/quality,q_90",
      "available": true,
      "rating": 4.5  
    },
    {
      "id": 12,
      "name": "USB 2.0 DataPlus, DENIZ",
      "price": 209,
      "size": 32,
      "demension": "23.1 x 10.3 x 2.2 mm",
      "speed": "4 Gbit/s",
      "material": "Metal",
      "image": "https://dkstatics-public.digikala.com/digikala-products/860efdbf714edc124c8439b36f0641342f3b598b_1692269113.jpg?x-oss-process=image/resize,m_lfit,h_800,w_800/format,webp/quality,q_90",
      "available": false,
      "rating": 5  
    },
    {
      "id": 13,
      "name": "Type-C PNY, DUO LINK 3.2",
      "price": 900,
      "size": 256,
      "demension": "63.4 x 19.2 x 9.7 mm",
      "speed": "15 Gbit/s",
      "material": "Steel",
      "image": "https://dkstatics-public.digikala.com/digikala-products/d55d11727a2e3701e2b3217e80df4f9e73e05fcd_1685435907.jpg?x-oss-process=image/resize,m_lfit,h_800,w_800/format,webp/quality,q_90",
      "available": true,
      "rating": 2.5  
    },
    {
      "id": 14,
      "name": "USB 2.0 Dahua, U106",
      "price": 202,
      "size": 64,
      "demension": "50.2 x 15.1 x 5.2 mm",
      "speed": "5 Gbit/s",
      "material": "Steel",
      "image": "https://dkstatics-public.digikala.com/digikala-products/c4142e214784e07771b4d7eb002078e7a2ff5390_1697454317.jpg?x-oss-process=image/resize,m_lfit,h_800,w_800/format,webp/quality,q_90",
      "available": true,
      "rating": 3.5  
    },
    {
      "id": 15,
      "name": "USB 2.0 PearLit, Dragon U-84",
      "price": 330,
      "size": 64,
      "demension": "60.4 x 17.7 x 8.5 mm",
      "speed": "6 Gbit/s",
      "material": "Plastic/Metal",
      "image": "https://dkstatics-public.digikala.com/digikala-products/881da45dbd20f223d49f456b09449d0c14111320_1649247981.jpg?x-oss-process=image/resize,m_lfit,h_800,w_800/format,webp/quality,q_90",
      "available": false,
      "rating": 4  
    },
    {
      "id": 16,
      "name": "USB 3.2 SanDisk, Ultra Eco™",
      "price": 400,
      "size": 64,
      "demension": "46.3 x 21.1 x 9.4 mm",
      "speed": "10 Gbit/s",
      "material": "Plastic",
      "image": "https://dkstatics-public.digikala.com/digikala-products/ab3ee8549e35f257ccfeaef65f477935b4bf0b5e_1670399883.jpg?x-oss-process=image/resize,m_lfit,h_800,w_800/format,webp/quality,q_90",
      "available": false,
      "rating": 3.5  
    },
    {
      "id": 17,
      "name": "USB 3.2 ADATA, UR340",
      "price": 590,
      "size": 128,
      "demension": "34.8 x 12.3 x 4.6 mm",
      "speed": "12 Gbit/s",
      "material": "Metal",
      "image": "https://dkstatics-public.digikala.com/digikala-products/a848a9ee5aca2dae1e854b6f636f8d1bfbc879fa_1699528186.jpg?x-oss-process=image/resize,m_lfit,h_800,w_800/format,webp/quality,q_90",
      "available": true,
      "rating": 5  
    },
    {
      "id": 18,
      "name": "USB 3.2 SanDisk, CZ550 CURVE",
      "price": 510,
      "size": 128,
      "demension": "100. x 50.1 x 20.5 mm",
      "speed": "15 Gbit/s",
      "material": "Plastic",
      "image": "https://dkstatics-public.digikala.com/digikala-products/4bdb5bccea1e6df85a1f506c0f929a424ef95ca0_1665788448.jpg?x-oss-process=image/resize,m_lfit,h_800,w_800/format,webp/quality,q_90",
      "available": false,
      "rating": 4.5  
    },
    {
      "id": 19,
      "name": "Type-C PNY, DUO LINK 3.2",
      "price": 889,
      "size": 128,
      "demension": "63.4 x 19.2 x 9.7 mm",
      "speed": "18 Gbit/s",
      "material": "Plastic",
      "image": "https://dkstatics-public.digikala.com/digikala-products/fc9c2da4a83e5a3111aea1d9de69a5cd4cc5e841_1685435563.jpg?x-oss-process=image/resize,m_lfit,h_800,w_800/format,webp/quality,q_90",
      "available": true,
      "rating": 4  
    },
    {
      "id": 20,
      "name": "USB 3.2 Kingston, EXODIA ONYX",
      "price": 238,
      "size": 64,
      "demension": "50.1 x 15.1 x 5.5 mm",
      "speed": "6 Gbit/s",
      "material": "Plastic",
      "image": "https://dkstatics-public.digikala.com/digikala-products/81d93d7542d62cf27c5081f42be41f4050781595_1696105406.jpg?x-oss-process=image/resize,m_lfit,h_800,w_800/format,webp/quality,q_90",
      "available": true,
      "rating": 3.5  
    },
    {
      "id": 21,
      "name": "USB 3.0 Verity, V811",
      "price": 396,
      "size": 64,
      "demension": "15.1 x 10.1 x 4.5 mm",
      "speed": "10 Gbit/s",
      "material": "Metal",
      "image": "https://dkstatics-public.digikala.com/digikala-products/e9e7ae8056e9f1492a005c2af87d5209eff1799e_1691051650.jpg?x-oss-process=image/resize,m_lfit,h_800,w_800/format,webp/quality,q_90",
      "available": false,
      "rating": 4  
    },
    {
      "id": 22,
      "name": "USB 3.1 PNY, Elite-X Fit",
      "price": 999,
      "size": 256,
      "demension": "63.4 x 19.2 x 9.7 mm",
      "speed": "16 Gbit/s",
      "material": "Plastic",
      "image": "https://dkstatics-public.digikala.com/digikala-products/8aeae383714bc33edf4e895d67a1fbe63f66b80f_1685452998.jpg?x-oss-process=image/resize,m_lfit,h_800,w_800/format,webp/quality,q_90",
      "available": true,
      "rating": 4.5  
    },
    {
      "id": 23,
      "name": "USB 3.2 ADATA, uv128",
      "price": 240,
      "size": 32,
      "demension": "60.1 x 20.1 x 9.5 mm",
      "speed": "4 Gbit/s",
      "material": "Plastic",
      "image": "https://dkstatics-public.digikala.com/digikala-products/34db05f29b8639aeb2172906f2df426744d6d253_1703591592.jpg?x-oss-process=image/resize,m_lfit,h_800,w_800/format,webp/quality,q_90",
      "available": true,
      "rating": 4.5  
    },
    {
      "id": 24,
      "name": "USB 3.0 Verity, V812",
      "price": 339,
      "size": 64,
      "demension": "15.1 x 10.1 x 4.2 mm",
      "speed": "5 Gbit/s",
      "material": "Metal",
      "image": "https://dkstatics-public.digikala.com/digikala-products/9a65ffcbd80273f3c7c920152ad08ecdfd9a399c_1691049288.jpg?x-oss-process=image/resize,m_lfit,h_800,w_800/format,webp/quality,q_90",
      "available": false,
      "rating": 3.5  
    },
    {
      "id": 25,
      "name": "USB 3.2 Verbatim, PinStripe",
      "price": 198,
      "size": 32,
      "demension": "55.1 x 19.1 x 7.5 mm",
      "speed": "5 Gbit/s",
      "material": "Plastic",
      "image": "https://dkstatics-public.digikala.com/digikala-products/0c43728d3829f42298b826817868c94fd293e71a_1712661415.jpg?x-oss-process=image/resize,m_lfit,h_800,w_800/format,webp/quality,q_90",
      "available": true,
      "rating": 3.5  
    },
    {
      "id": 26,
      "name": "USB 3.0 Verity, V813",
      "price": 340,
      "size": 32,
      "demension": "25.1 x 10.1 x 5.5 mm",
      "speed": "5 Gbit/s",
      "material": "Metal",
      "image": "https://dkstatics-public.digikala.com/digikala-products/c29b9dcf7a4db1690a316241cc1077d10796c338_1614351871.jpg?x-oss-process=image/resize,m_lfit,h_800,w_800/format,webp/quality,q_90",
      "available": false,
      "rating": 5  
    },
    {
      "id": 27,
      "name": "Type-C QueenTech, C-PLUS",
      "price": 273,
      "size": 32,
      "demension": "20.1 x 12.1 x 5.5 mm",
      "speed": "4 Gbit/s",
      "material": "Plastic",
      "image": "https://dkstatics-public.digikala.com/digikala-products/bffd916c99f05e38b50b8451061618f4cd044b9d_1641200088.jpg?x-oss-process=image/resize,m_lfit,h_800,w_800/format,webp/quality,q_90",
      "available": true,
      "rating": 1.5  
    },
    {
      "id": 28,
      "name": "USB 3.2 TeamGroup, C211",
      "price": 394,
      "size": 64,
      "demension": "49.1 x 20.1 x 5.5 mm",
      "speed": "8 Gbit/s",
      "material": "Plastic",
      "image": "https://dkstatics-public.digikala.com/digikala-products/fcd9b733a7505f57819da8cd4b011f902723685e_1638896120.jpg?x-oss-process=image/resize,m_lfit,h_800,w_800/format,webp/quality,q_90",
      "available": true,
      "rating": 4.5  
    }
  ]
}